relax/__init__.py
relax/app.py
relax/config.py
relax/html.py
relax/injection.py
relax/js/hmr_reload.js
relax/py.typed
relax/server.py
relax/test.py
relax_py-0.6.2.dist-info/LICENSE
relax_py-0.6.2.dist-info/METADATA
relax_py-0.6.2.dist-info/WHEEL
relax_py-0.6.2.dist-info/RECORD
