Metadata-Version: 2.1
Name: relax-py
Version: 0.6.2
Summary: 
Author: crpier
Author-email: crpier42@gmail.com
Requires-Python: >=3.11,<4.0
Classifier: Programming Language :: Python :: 3
Classifier: Programming Language :: Python :: 3.11
Classifier: Programming Language :: Python :: 3.12
Requires-Dist: beautifulsoup4 (>=4.12.2,<5.0.0)
Requires-Dist: pydantic-settings (>=2.3.4,<3.0.0)
Requires-Dist: starlette (>=0.31.1,<0.32.0)
Requires-Dist: typing-extensions (>=4.8.0,<5.0.0)
Requires-Dist: uvicorn[standard] (>=0.29.0,<0.30.0)
Requires-Dist: watchfiles (>=0.21.0,<0.22.0)
